xvc-0.6.17.dist-info/METADATA
xvc-0.6.17.dist-info/WHEEL
xvc-0.6.17.dist-info/licenses/LICENSE
xvc/__init__.py
xvc/xvc.pyd
xvc-0.6.17.dist-info/RECORD
